safer/__init__.py
safer/api.py
safer/crawler.py
safer/exceptions.py
safer/html.py
safer/results.py
safer/search.py
python_safer-2.0.dist-info/LICENSE
python_safer-2.0.dist-info/METADATA
python_safer-2.0.dist-info/WHEEL
python_safer-2.0.dist-info/top_level.txt
python_safer-2.0.dist-info/RECORD
