Metadata-Version: 2.1
Name: python-safer
Version: 2.0
Summary: A web scraping API written in Python to fetch data from the Department of Transportation's Safety and Fitness Electronic Records System http://www.safersys.org/
Home-page: https://github.com/arthurtyukayev/python-safer
Author: Arthur Tyukayev
Author-email: arthurtyukayev@gmail.com
License: MIT
Keywords: SAFER safer department transportation fitness electronic records system
License-File: LICENSE
Requires-Dist: lxml
Requires-Dist: requests
Requires-Dist: python-dateutil
